AUTHORS.rst
CHANGES.rst
MANIFEST.in
README.rst
setup.cfg
setup.py
docs/Makefile
docs/libpeerconnection.log
docs/make.bat
docs/source/AUTHORS.rst
docs/source/advanced.rst
docs/source/api.rst
docs/source/basic.rst
docs/source/conf.py
docs/source/index.rst
pytest_sauce/__init__.py
pytest_sauce/command.py
pytest_sauce/default.yaml
pytest_sauce/utils.py
pytest_sauce.egg-info/PKG-INFO
pytest_sauce.egg-info/SOURCES.txt
pytest_sauce.egg-info/dependency_links.txt
pytest_sauce.egg-info/entry_points.txt
pytest_sauce.egg-info/not-zip-safe
pytest_sauce.egg-info/requires.txt
pytest_sauce.egg-info/top_level.txt
tests/__init__.py