Metadata-Version: 1.1
Name: pytest-sauce
Version: 0.3.2
Summary: pytest_sauce provides sane and helpful methods worked
Home-page: https://github.com/ClearcodeHQ/pytest_sauce
Author: Clearcode - The A Room
Author-email: thearoom@clearcode.cc
License: UNKNOWN
Keywords: pytest mozwebqa selenium saucelabs
Platform: UNKNOWN
Classifier: Development Status :: 3 - Alpha
Classifier: Environment :: Web Environment
Classifier: Environment :: Console
Classifier: Intended Audience :: Developers
Classifier: License :: Public Domain
Classifier: Natural Language :: English
Classifier: Operating System :: OS Independent
Classifier: Programming Language :: Python
Classifier: Programming Language :: Python :: 2.7
Classifier: Topic :: Software Development :: Testing
